setup.py
CryDeer/controller.py
CryDeer/crydeer.py
CryDeer/database.py
CryDeer.egg-info/PKG-INFO
CryDeer.egg-info/SOURCES.txt
CryDeer.egg-info/dependency_links.txt
CryDeer.egg-info/entry_points.txt
CryDeer.egg-info/requires.txt
CryDeer.egg-info/top_level.txt
CryDeer.egg-info/zip-safe