Metadata-Version: 1.0
Name: CryDeer
Version: 0.2.5.2
Summary: a command line express package helper
Home-page: https://github.com/vimsucks/CryDeer
Author: vimsucks
Author-email: reg@vimsucks.com
License: GPLv3
Keywords: python express package helper
Platform: UNKNOWN
